markalgo/__init__.py
markalgo/__main__.py
markalgo/console.py
markalgo/processing.py
markalgo/rules.py
markalgo-1.0.2.dist-info/DESCRIPTION.rst
markalgo-1.0.2.dist-info/METADATA
markalgo-1.0.2.dist-info/RECORD
markalgo-1.0.2.dist-info/WHEEL
markalgo-1.0.2.dist-info/entry_points.txt
markalgo-1.0.2.dist-info/metadata.json
markalgo-1.0.2.dist-info/top_level.txt
